pyuscf/__init__.py
pyuscf/exception.py
pyuscf/formatifier.py
pyuscf/msa.py
pyuscf-0.2.1.dist-info/LICENSE
pyuscf-0.2.1.dist-info/WHEEL
pyuscf-0.2.1.dist-info/METADATA
pyuscf-0.2.1.dist-info/RECORD
