Metadata-Version: 2.1
Name: pyuscf
Version: 0.2.1
Summary: USCF Member Service Area (MSA) for Python
Home-page: https://gitlab.com/skibur/pyuscf
License: GPL-2.0
Keywords: uscf,msa,chess,rating
Author: Juan Antonio Sauceda
Author-email: jasgordo@gmail.com
Requires-Python: >=3.6,<4.0
Classifier: Environment :: Console
Classifier: Intended Audience :: Developers
Classifier: License :: OSI Approved :: GNU General Public License (GPL)
Classifier: License :: OSI Approved :: GNU General Public License v2 (GPLv2)
Classifier: Natural Language :: English
Classifier: Operating System :: OS Independent
Classifier: Programming Language :: Python
Classifier: Programming Language :: Python :: 3
Classifier: Programming Language :: Python :: 3.6
Classifier: Programming Language :: Python :: 3.7
Classifier: Topic :: Internet :: WWW/HTTP
Classifier: Topic :: Software Development :: Libraries :: Python Modules
Requires-Dist: bs4 (>=0.0.1,<0.0.2)
Project-URL: Documentation, https://gitlab.com/skibur/pyuscf
Project-URL: Repository, https://gitlab.com/skibur/pyuscf
